sumo/__init__.py
sumo/cli/__init__.py
sumo/cli/bandplot.py
sumo/cli/bandstats.py
sumo/cli/dosplot.py
sumo/cli/kgen.py
sumo/cli/optplot.py
sumo/cli/phonon_bandplot.py
sumo/electronic_structure/__init__.py
sumo/electronic_structure/bandstructure.py
sumo/electronic_structure/dos.py
sumo/electronic_structure/effective_mass.py
sumo/electronic_structure/optics.py
sumo/io/__init__.py
sumo/io/castep.py
sumo/io/questaal.py
sumo/io/vasp.py
sumo/phonon/__init__.py
sumo/phonon/phonopy.py
sumo/plotting/__init__.py
sumo/plotting/bs_plotter.py
sumo/plotting/dos_plotter.py
sumo/plotting/optics_plotter.py
sumo/plotting/orbital_colours.conf
sumo/plotting/phonon_bs_plotter.py
sumo/plotting/sumo_base.mplstyle
sumo/plotting/sumo_bs.mplstyle
sumo/plotting/sumo_dos.mplstyle
sumo/plotting/sumo_optics.mplstyle
sumo/plotting/sumo_phonon.mplstyle
sumo/symmetry/__init__.py
sumo/symmetry/brad_crack_kpath.py
sumo/symmetry/bradcrack.json
sumo/symmetry/custom_kpath.py
sumo/symmetry/kpath.py
sumo/symmetry/kpoints.py
sumo/symmetry/latimer_munro_kpath.py
sumo/symmetry/pymatgen_kpath.py
sumo/symmetry/seekpath_kpath.py
sumo2-0.0.1.data/data/LICENSE
sumo2-0.0.1.data/data/orbital_colours.conf
sumo2-0.0.1.dist-info/LICENSE
sumo2-0.0.1.dist-info/METADATA
sumo2-0.0.1.dist-info/WHEEL
sumo2-0.0.1.dist-info/entry_points.txt
sumo2-0.0.1.dist-info/top_level.txt
sumo2-0.0.1.dist-info/RECORD
