Metadata-Version: 2.1
Name: sumo2
Version: 0.0.1
Summary: Heavy weight plotting tools for ab initio solid-state calculations
Home-page: https://github.com/smtg-ucl/sumo
Author: Alex Ganose, Adam J. Jackson
Author-email: d.scanlon@ucl.ac.uk
License: MIT
Keywords: chemistry pymatgen dft vasp dos band
Classifier: Development Status :: 5 - Production/Stable
Classifier: Intended Audience :: Science/Research
Classifier: License :: OSI Approved :: MIT License
Classifier: Natural Language :: English
Classifier: Programming Language :: Python :: 3 :: Only
Classifier: Programming Language :: Python :: 3.5
Classifier: Topic :: Scientific/Engineering :: Chemistry
Classifier: Topic :: Scientific/Engineering :: Physics
Requires-Python: >=3.8
License-File: LICENSE
Requires-Dist: spglib
Requires-Dist: numpy
Requires-Dist: scipy
Requires-Dist: h5py
Requires-Dist: pymatgen >=2020.10.20
Requires-Dist: phonopy >=2.1.3
Requires-Dist: matplotlib >=3.2.0
Requires-Dist: seekpath
Requires-Dist: castepxbin <1.0
Requires-Dist: colormath
Requires-Dist: importlib-resources
Provides-Extra: dev
Requires-Dist: pre-commit ; extra == 'dev'
Provides-Extra: docs
Requires-Dist: sphinx ; extra == 'docs'
Requires-Dist: sphinx-argparse ; extra == 'docs'
Provides-Extra: tests
Requires-Dist: pytest ; extra == 'tests'
